rheodata/__init__.py
rheodata/data_converter.py
rheodata/extractors/ARES_G2.py
rheodata/extractors/__init__.py
rheodata/extractors/antonpaar.py
rheodata/extractors/data_converter.py
rheodata-0.0.8.dist-info/LICENSE
rheodata-0.0.8.dist-info/METADATA
rheodata-0.0.8.dist-info/WHEEL
rheodata-0.0.8.dist-info/top_level.txt
rheodata-0.0.8.dist-info/RECORD
