Metadata-Version: 2.1
Name: rheodata
Version: 0.0.8
Summary: Packge to help process rheology data
Home-page: https://github.com/desdelgado/rheology-data-toolkit
Author: David Delgado
Author-email: daviddelgado2020@u.northwestern.com
License: UNKNOWN
Platform: UNKNOWN
Classifier: Programming Language :: Python :: 3
Classifier: License :: OSI Approved :: MIT License
Classifier: Operating System :: OS Independent
Requires-Python: >=3.6
Requires-Dist: h5py (>=2.10.0)
Requires-Dist: tables (>=3.6.1)
Requires-Dist: jsonschema (>=3.2.0)
Requires-Dist: pickleshare (>=0.7.5)
Requires-Dist: pandas (>=1.0.4)
Requires-Dist: xlrd (>=1.2.0)
